helpscript/__init__.py
helpscript/main.py
helpscript-1.0.0.dist-info/LICENSE
helpscript-1.0.0.dist-info/METADATA
helpscript-1.0.0.dist-info/WHEEL
helpscript-1.0.0.dist-info/top_level.txt
helpscript-1.0.0.dist-info/RECORD
