Metadata-Version: 2.1
Name: helpscript
Version: 1.0.0
Summary: A helpscript For Python Projects
Home-page: https://github.com/toxic-noob/helpscript
Author: OmniTotal
Author-email: officialomnitotal@gmail.com
Project-URL: Bug Tracker, https://github.com/toxic-noob/helpscript/issues
Classifier: Programming Language :: Python :: 3
Classifier: License :: OSI Approved :: MIT License
Classifier: Operating System :: OS Independent
Requires-Python: >=3.6
License-File: LICENSE
